zttt/__init__.py
zttt/_zt_core/__init__.py
zttt/_zt_core/zt_base_board.py
zttt/_zt_core/zt_base_engine.py
zttt/_zt_core/zt_engine_first.py
zttt/_zt_core/zt_player_first.py
zttt/pvc.py
zttt/pvp.py
zttt/zt_errors.py
zttt-1.0.2.dist-info/LICENSE
zttt-1.0.2.dist-info/METADATA
zttt-1.0.2.dist-info/WHEEL
zttt-1.0.2.dist-info/RECORD
