Metadata-Version: 2.1
Name: zttt
Version: 1.0.2
Summary: Simple, Standalone Tic Tac Toe Library
Home-page: https://ztictactoe.readthedocs.io/en/latest/
License: MIT
Keywords: ZTTT,TTT,Tic Tac Toe,X-O,poetry,sphinx
Author: Sumanth NR
Author-email: sumanthnr62@gmail.com
Requires-Python: >=3.7,<4.0
Classifier: License :: OSI Approved :: MIT License
Classifier: Programming Language :: Python :: 3
Classifier: Programming Language :: Python :: 3.7
Classifier: Programming Language :: Python :: 3.8
Classifier: Programming Language :: Python :: 3.9
Classifier: Programming Language :: Python :: 3.10
Classifier: Programming Language :: Python :: 3.11
Project-URL: Documentation, https://ztictactoe.readthedocs.io/en/v1/
Project-URL: Repository, https://github.com/Sigma1084/ZTicTacToe/tree/v1
